Metadata-Version: 2.4
Name: lmdeploy
Version: 0.11.1
Summary: A toolset for compressing, deploying and serving LLM
Author: OpenMMLab
Author-email: openmmlab@gmail.com
Classifier: Programming Language :: Python :: 3.9
Classifier: Programming Language :: Python :: 3.10
Classifier: Programming Language :: Python :: 3.11
Classifier: Programming Language :: Python :: 3.12
Classifier: Programming Language :: Python :: 3.13
Classifier: Intended Audience :: Developers
Classifier: Intended Audience :: Education
Classifier: Intended Audience :: Science/Research
License-File: LICENSE
Requires-Dist: accelerate>=0.29.3
Requires-Dist: aiohttp
Requires-Dist: cloudpickle
Requires-Dist: einops
Requires-Dist: fastapi
Requires-Dist: fire
Requires-Dist: mmengine-lite
Requires-Dist: numpy
Requires-Dist: openai
Requires-Dist: openai_harmony
Requires-Dist: partial_json_parser
Requires-Dist: peft<=0.14.0
Requires-Dist: pillow
Requires-Dist: prometheus_client
Requires-Dist: protobuf
Requires-Dist: pybase64
Requires-Dist: pydantic>2.0.0
Requires-Dist: pyzmq
Requires-Dist: ray
Requires-Dist: safetensors
Requires-Dist: sentencepiece
Requires-Dist: shortuuid
Requires-Dist: tiktoken
Requires-Dist: torch<=2.8.0,>=2.0.0
Requires-Dist: torchvision<=0.23.0,>=0.15.0
Requires-Dist: transformers
Requires-Dist: triton<=3.4.0,>=3.0.0; sys_platform == "linux" and "aarch64" not in platform_machine and "arm" not in platform_machine
Requires-Dist: uvicorn
Requires-Dist: xgrammar
Requires-Dist: nvidia-nccl-cu12
Requires-Dist: nvidia-cuda-runtime-cu12
Requires-Dist: nvidia-cublas-cu12
Requires-Dist: nvidia-curand-cu12
Provides-Extra: all
Requires-Dist: cmake_build_extension; extra == "all"
Requires-Dist: pybind11<=2.13.1; extra == "all"
Requires-Dist: setuptools; extra == "all"
Requires-Dist: accelerate>=0.29.3; extra == "all"
Requires-Dist: aiohttp; extra == "all"
Requires-Dist: cloudpickle; extra == "all"
Requires-Dist: einops; extra == "all"
Requires-Dist: fastapi; extra == "all"
Requires-Dist: fire; extra == "all"
Requires-Dist: mmengine-lite; extra == "all"
Requires-Dist: numpy; extra == "all"
Requires-Dist: openai; extra == "all"
Requires-Dist: openai_harmony; extra == "all"
Requires-Dist: partial_json_parser; extra == "all"
Requires-Dist: peft<=0.14.0; extra == "all"
Requires-Dist: pillow; extra == "all"
Requires-Dist: prometheus_client; extra == "all"
Requires-Dist: protobuf; extra == "all"
Requires-Dist: pybase64; extra == "all"
Requires-Dist: pydantic>2.0.0; extra == "all"
Requires-Dist: pyzmq; extra == "all"
Requires-Dist: ray; extra == "all"
Requires-Dist: safetensors; extra == "all"
Requires-Dist: sentencepiece; extra == "all"
Requires-Dist: shortuuid; extra == "all"
Requires-Dist: tiktoken; extra == "all"
Requires-Dist: torch<=2.8.0,>=2.0.0; extra == "all"
Requires-Dist: torchvision<=0.23.0,>=0.15.0; extra == "all"
Requires-Dist: transformers; extra == "all"
Requires-Dist: triton<=3.4.0,>=3.0.0; (sys_platform == "linux" and "aarch64" not in platform_machine and "arm" not in platform_machine) and extra == "all"
Requires-Dist: uvicorn; extra == "all"
Requires-Dist: xgrammar; extra == "all"
Requires-Dist: accelerate; extra == "all"
Requires-Dist: datasets; extra == "all"
Requires-Dist: transformers_stream_generator; extra == "all"
Requires-Dist: aiohttp; extra == "all"
Requires-Dist: prometheus_client; extra == "all"
Requires-Dist: protobuf; extra == "all"
Requires-Dist: timm; extra == "all"
Provides-Extra: lite
Requires-Dist: accelerate; extra == "lite"
Requires-Dist: datasets; extra == "lite"
Requires-Dist: transformers_stream_generator; extra == "lite"
Provides-Extra: serve
Requires-Dist: aiohttp; extra == "serve"
Requires-Dist: prometheus_client; extra == "serve"
Requires-Dist: protobuf; extra == "serve"
Requires-Dist: timm; extra == "serve"
Dynamic: author
Dynamic: author-email
Dynamic: classifier
Dynamic: description
Dynamic: description-content-type
Dynamic: license-file
Dynamic: provides-extra
Dynamic: requires-dist
Dynamic: summary
